setup.cfg
setup.py
poormanslogging/__init__.py
poormanslogging.egg-info/PKG-INFO
poormanslogging.egg-info/SOURCES.txt
poormanslogging.egg-info/dependency_links.txt
poormanslogging.egg-info/requires.txt
poormanslogging.egg-info/top_level.txt