Metadata-Version: 1.1
Name: poormanslogging
Version: 1.1
Summary: Dirt simple logging
Home-page: https://github.com/nicovillanueva/poormanslogging
Author: Nicolas Villanueva
Author-email: villanueva.arg@gmail.com
License: GPLv2+
Keywords: logging zeroconfig
Platform: UNKNOWN
Classifier: Development Status :: 5 - Production/Stable
Classifier: Environment :: Console
Classifier: Programming Language :: Python :: 3
Classifier: Intended Audience :: Developers
